Student990900811/Student990900811.py
Student990900811/__init__.py
student990900811-1.2.dist-info/METADATA
student990900811-1.2.dist-info/WHEEL
student990900811-1.2.dist-info/top_level.txt
student990900811-1.2.dist-info/RECORD
